phonetic_id.py
phonetic_id-1.0.0.dist-info/licenses/LICENSE
phonetic_id-1.0.0.dist-info/METADATA
phonetic_id-1.0.0.dist-info/WHEEL
phonetic_id-1.0.0.dist-info/top_level.txt
phonetic_id-1.0.0.dist-info/RECORD
