Metadata-Version: 2.4
Name: phonetic-id
Version: 1.0.0
Summary: Phonetic ID is a lightweight package for generating a easy to say ID.
Home-page: https://github.com/0x1618/phonetic-id
Author: Maksymilian Sawicz
Classifier: Programming Language :: Python :: 3
Classifier: License :: OSI Approved :: MIT License
Classifier: Operating System :: OS Independent
Requires-Python: >=3.10
License-File: LICENSE
Dynamic: author
Dynamic: classifier
Dynamic: description
Dynamic: description-content-type
Dynamic: home-page
Dynamic: license-file
Dynamic: requires-python
Dynamic: summary
